fuwujiqiren/__init__.py
fuwujiqiren/mov_charge.py
fuwujiqiren/mov_point.py
fuwujiqiren/mov_set_point.py
fuwujiqiren-1.0.dist-info/METADATA
fuwujiqiren-1.0.dist-info/WHEEL
fuwujiqiren-1.0.dist-info/top_level.txt
fuwujiqiren-1.0.dist-info/RECORD
