Metadata-Version: 2.4
Name: fuwujiqiren
Version: 1.0
Summary: A Powerful Windows-PC-Wechat automation Tool
Home-page: https://github.com/Hello-Mr-Crab/pywechat
License: Apache-2.0
Keywords: rpa,windows,wechat,automation
Dynamic: description
Dynamic: description-content-type
Dynamic: home-page
Dynamic: keywords
Dynamic: license
Dynamic: summary
